fer_pytorch/VERSION
fer_pytorch/__init__.py
fer_pytorch/augmentations.py
fer_pytorch/fer.py
fer_pytorch/model.py
fer_pytorch/pre_trained_models.py
fer_pytorch/run_trainer.py
fer_pytorch/train.py
fer_pytorch/train_test_dataset.py
fer_pytorch/utils/__init__.py
fer_pytorch/utils/utils.py
fer_pytorch-1.1.2.dist-info/LICENSE.md
fer_pytorch-1.1.2.dist-info/METADATA
fer_pytorch-1.1.2.dist-info/WHEEL
fer_pytorch-1.1.2.dist-info/top_level.txt
fer_pytorch-1.1.2.dist-info/RECORD
