Metadata-Version: 2.1
Name: fer-pytorch
Version: 1.1.2
Summary: Facial Expression Recognition package implemented in Pytorch.
Home-page: https://github.com/Emilien-mipt/fer-pytorch
Author: Emin Tagiev
Author-email: emin.tagiev@phystech.edu
License: MIT
Platform: UNKNOWN
Classifier: License :: OSI Approved :: MIT License
Classifier: Intended Audience :: Developers
Classifier: Intended Audience :: Science/Research
Classifier: Programming Language :: Python
Classifier: Programming Language :: Python :: 3
Classifier: Programming Language :: Python :: Implementation :: PyPy
Classifier: Topic :: Software Development :: Libraries
Classifier: Topic :: Software Development :: Libraries :: Python Modules
Requires-Python: >=3.6.0
License-File: LICENSE.md
Requires-Dist: albumentations (<=1.0.0,>=0.5.2)
Requires-Dist: facenet-pytorch (==2.5.2)
Requires-Dist: hydra-core (==1.1.1)
Requires-Dist: matplotlib (<=3.5.1,>=3.3.4)
Requires-Dist: numpy (<=1.22,>=1.19.5)
Requires-Dist: opencv-python (<=4.5.5.64,>=4.5.1.48)
Requires-Dist: pandas (<=1.4.2,>=1.1.5)
Requires-Dist: Pillow (<=8.4.0,>=8.1.2)
Requires-Dist: pytorch-lightning (==1.5.10)
Requires-Dist: scikit-learn (<=1.0,>=0.24.1)
Requires-Dist: timm (<=0.5.4,>=0.3.2)
Requires-Dist: torch (<=1.11,>=1.8.0)
Requires-Dist: tqdm (<=4.63.0,>=4.59.0)
